{
  "1": "grass",
  "2": "water",
  "3": "fire",
  "4": "flying",
  "5": "electric",
  "6": "steel",
  "7": "ground",
  "8": "normal",
  "9": "ice",
  "10": "psychic",
  "11": "fight",
  "12": "light",
  "13": "dark",
  "14": "myth",
  "15": "dragon",
  "16": "saint",
  "17": "dimension",
  "18": "ancient",
  "19": "demon",
  "20": "nature",
  "21": "grass_psychic",
  "22": "grass_fight",
  "23": "grass_dark",
  "24": "water_psychic",
  "25": "water_dark",
  "26": "water_dragon",
  "27": "fire_flying",
  "28": "fire_dragon",
  "29": "fire_psychic",
  "30": "flying_psychic",
  "31": "flying_light",
  "32": "flying_dragon",
  "33": "electric_fire",
  "34": "electric_ice",
  "35": "electric_fight",
  "36": "electric_dark",
  "37": "steel_ground",
  "38": "steel_psychic",
  "39": "steel_dragon",
  "40": "ground_dragon",
  "41": "ground_fight",
  "42": "ground_dark",
  "43": "ice_dragon",
  "44": "ice_light",
  "45": "ice_dark",
  "46": "psychic_ice",
  "47": "fight_fire",
  "48": "fight_dark",
  "49": "light_myth",
  "50": "dark_myth",
  "51": "myth_psychic",
  "52": "saint_light",
  "53": "flying_myth",
  "54": "ground_psychic",
  "55": "dark_dragon",
  "56": "saint_dark",
  "57": "ancient_fight",
  "58": "myth_fire",
  "59": "light_fight",
  "60": "myth_fight",
  "61": "dimension_fight",
  "62": "demon_myth",
  "63": "ancient_dragon",
  "64": "light_dimension",
  "65": "ancient_saint",
  "66": "water_fight",
  "67": "electric_dragon",
  "68": "light_fire",
  "69": "light_dark",
  "70": "demon_dragon",
  "71": "ancient_myth",
  "72": "steel_dimension",
  "73": "fight_dragon",
  "74": "fight_nature",
  "75": "demon_steel",
  "76": "electric_dimension",
  "77": "ancient_fire",
  "78": "saint_fight",
  "79": "saint_dimension",
  "80": "saint_electric",
  "81": "ancient_ground",
  "82": "ancient_grass",
  "83": "nature_dragon",
  "84": "ice_myth",
  "85": "flying_dark",
  "86": "ice_fire",
  "87": "ice_flying",
  "88": "nature_saint",
  "89": "chaos_saint",
  "90": "ancient_demon",
  "91": "nature_ice",
  "92": "chaos_dark",
  "93": "chaos_fight",
  "94": "chaos_psychic",
  "95": "saint_psychic",
  "96": "chaos_ground",
  "97": "dark_demon",
  "98": "chaos_ancient",
  "99": "chaos_demon",
  "100": "saint_ground",
  "101": "fire_dark",
  "102": "light_psychic",
  "103": "steel_fight",
  "104": "normal",
  "105": "normal",
  "106": "normal",
  "107": "normal",
  "108": "normal",
  "109": "normal",
  "110": "normal",
  "111": "normal",
  "112": "normal",
  "113": "normal",
  "114": "normal",
  "115": "normal",
  "116": "normal",
  "117": "normal",
  "118": "normal",
  "119": "normal",
  "120": "normal",
  "121": "normal",
  "122": "normal",
  "123": "normal",
  "124": "normal",
  "125": "normal",
  "126": "normal",
  "127": "normal",
  "128": "normal",
  "129": "normal",
  "130": "normal",
  "131": "normal",
  "132": "normal",
  "133": "normal",
  "134": "normal",
  "135": "normal",
  "136": "normal",
  "137": "normal",
  "138": "normal"
}